blacksql/__init__.py
blacksql/__main__.py
blacksql/core.py
blacksql-0.1.0.dist-info/WHEEL
blacksql-0.1.0.dist-info/METADATA
blacksql-0.1.0.dist-info/RECORD
